README.rst
setup.py
wfw/__init__.py
wfw/__main__.py
wfw/api.py
wfw/commands.py
wfw/lib.py
wfw/tree.py
wfw/wfexceptions.py
wfw.egg-info/PKG-INFO
wfw.egg-info/SOURCES.txt
wfw.egg-info/dependency_links.txt
wfw.egg-info/entry_points.txt
wfw.egg-info/pbr.json
wfw.egg-info/requires.txt
wfw.egg-info/top_level.txt