Metadata-Version: 1.1
Name: wfw
Version: 0.3.0
Summary: command-line interface for WorkFlowy
Home-page: https://github.com/kvch/wfw
Author: Noemi Vanyi
Author-email: sitbackandwait@gmail.com
License: GNU General Public License v3
Download-URL: https://github.com/kvch/wfw/tarball/0.3.0
Platform: UNKNOWN
Classifier: Development Status :: 4 - Beta
Classifier: License :: OSI Approved :: GNU General Public License v3 (GPLv3)
Classifier: Programming Language :: Python :: 2.7
